robotsuite/__init__.py
robotsuite-3.0.0.dist-info/METADATA
robotsuite-3.0.0.dist-info/WHEEL
robotsuite-3.0.0.dist-info/licenses/LICENSE.txt
robotsuite-3.0.0.dist-info/RECORD
