Metadata-Version: 2.4
Name: robotsuite
Version: 3.0.0
Summary: Robot Framework test suite for Python unittest framework
Project-URL: Repository, https://github.com/collective/robotsuite
Author-email: Asko Soukka <asko.soukka@iki.fi>
License: GPL-2.0-only
License-File: LICENSE.txt
Classifier: License :: OSI Approved :: GNU General Public License v2 (GPLv2)
Classifier: Programming Language :: Python :: 3
Requires-Python: >=3.9
Requires-Dist: importlib-metadata
Requires-Dist: lxml
Requires-Dist: robotframework
Provides-Extra: rf304
Requires-Dist: robotframework==3.0.4; extra == 'rf304'
Provides-Extra: rf312
Requires-Dist: robotframework==3.1.2; extra == 'rf312'
Provides-Extra: rf322
Requires-Dist: robotframework==3.2.2; extra == 'rf322'
Provides-Extra: rf403
Requires-Dist: robotframework==4.0.3; extra == 'rf403'
Provides-Extra: rf413
Requires-Dist: robotframework==4.1.3; extra == 'rf413'
Provides-Extra: rf501
Requires-Dist: robotframework==5.0.1; extra == 'rf501'
Provides-Extra: rf602
Requires-Dist: robotframework==6.0.2; extra == 'rf602'
Provides-Extra: rf611
Requires-Dist: robotframework==6.1.1; extra == 'rf611'
Provides-Extra: rf701
Requires-Dist: robotframework==7.0.1; extra == 'rf701'
Provides-Extra: rf711
Requires-Dist: robotframework==7.1.1; extra == 'rf711'
Provides-Extra: rf722
Requires-Dist: robotframework==7.2.2; extra == 'rf722'
Provides-Extra: test
